{"meta":{"name":"LIVE-PPV-EVENTS","id":"joe22","type":"channel","posterShape":"landscape","videos":[{"id":"joe2stream_2_0","title":"UFC TV HD"},{"id":"joe2stream_2_1","title":"WWE"},{"id":"joe2stream_2_2","title":"BOX NATION"},{"id":"joe2stream_2_3","title":"FOX ACTION"},{"id":"joe2stream_2_4","title":".Showtime."},{"id":"joe2stream_2_5","title":"ESPN DEPORTE"},{"id":"joe2stream_2_6","title":"ESPN-USA"},{"id":"joe2stream_2_7","title":"ESPN+"},{"id":"joe2stream_2_8","title":"ESPN."},{"id":"joe2stream_2_9","title":"SPACE-HD."},{"id":"joe2stream_2_10","title":"LAS ESTRELLAS"},{"id":"joe2stream_2_11","title":"AZTECA-7"},{"id":"joe2stream_2_12","title":"ESPN PLUS HD."}]}}